{
  "theme": [
    {
      "Questions": [
        {
          "Question": "What is the process of restoring and preserving old films called?",
          "TrueAnswer": "Film restoration",
          "FalseAnswer": [
            "Film remastering",
            "Film preservation",
            "Film digitization"
          ],
          "Explanation": "Film restoration is the process of repairing and preserving old films to their original quality."
        },
        {
          "Question": "Which organization is responsible for film preservation in the United States?",
          "TrueAnswer": "Library of Congress",
          "FalseAnswer": [
            "National Archives",
            "Smithsonian Institution",
            "American Film Institute"
          ],
          "Explanation": "The Library of Congress is the primary organization responsible for film preservation in the United States."
        },
        {
          "Question": "What is the purpose of film restoration and preservation?",
          "TrueAnswer": "To protect and maintain film history",
          "FalseAnswer": [
            "To make old films look modern",
            "To increase film revenue",
            "To promote new filmmakers"
          ],
          "Explanation": "The purpose of film restoration and preservation is to protect and maintain the history of cinema for future generations."
        },
        {
          "Question": "Which film format is most commonly used for film restoration and preservation?",
          "TrueAnswer": "35mm",
          "FalseAnswer": [
            "VHS",
            "DVD",
            "Blu-ray"
          ],
          "Explanation": "35mm film is the most commonly used format for film restoration and preservation due to its high quality."
        },
        {
          "Question": "What is the term for the decay and deterioration of old film stock?",
          "TrueAnswer": "Film degradation",
          "FalseAnswer": [
            "Film erosion",
            "Film corrosion",
            "Film disintegration"
          ],
          "Explanation": "Film degradation refers to the decay and deterioration of old film stock over time."
        },
        {
          "Question": "Which film preservation technique involves transferring film to a digital format?",
          "TrueAnswer": "Film digitization",
          "FalseAnswer": [
            "Film colorization",
            "Film stabilization",
            "Film reformatting"
          ],
          "Explanation": "Film digitization is a preservation technique that involves transferring film to a digital format for long-term storage and accessibility."
        },
        {
          "Question": "What is the purpose of film colorization in film restoration?",
          "TrueAnswer": "To add color to black and white films",
          "FalseAnswer": [
            "To remove color from color films",
            "To enhance film resolution",
            "To reduce film grain"
          ],
          "Explanation": "Film colorization is used to add color to black and white films, giving them a more modern look."
        },
        {
          "Question": "Which film preservation technique involves repairing physical damage to film stock?",
          "TrueAnswer": "Film repair",
          "FalseAnswer": [
            "Film cleaning",
            "Film duplication",
            "Film splicing"
          ],
          "Explanation": "Film repair is a preservation technique that involves repairing physical damage to film stock, such as tears or scratches."
        },
        {
          "Question": "What is the purpose of film duplication in film preservation?",
          "TrueAnswer": "To create backup copies of films",
          "FalseAnswer": [
            "To convert film to a digital format",
            "To enhance film quality",
            "To remove film imperfections"
          ],
          "Explanation": "Film duplication is used to create backup copies of films, ensuring their preservation in case of damage or loss."
        },
        {
          "Question": "Which film preservation technique involves stabilizing shaky footage?",
          "TrueAnswer": "Film stabilization",
          "FalseAnswer": [
            "Film editing",
            "Film restoration",
            "Film projection"
          ],
          "Explanation": "Film stabilization is a preservation technique that involves stabilizing shaky footage to improve its watchability."
        },
        {
          "Question": "What is the purpose of film projection in film restoration?",
          "TrueAnswer": "To showcase restored films in theaters",
          "FalseAnswer": [
            "To convert film to a digital format",
            "To preserve film history",
            "To distribute films to home viewers"
          ],
          "Explanation": "Film projection is used to showcase restored films in theaters, allowing audiences to experience them as they were originally intended."
        },
        {
          "Question": "Which film preservation technique involves removing dirt and dust from film stock?",
          "TrueAnswer": "Film cleaning",
          "FalseAnswer": [
            "Film rewinding",
            "Film scanning",
            "Film editing"
          ],
          "Explanation": "Film cleaning is a preservation technique that involves removing dirt and dust from film stock to improve its visual quality."
        },
        {
          "Question": "What is the purpose of film scanning in film restoration?",
          "TrueAnswer": "To create digital copies of films",
          "FalseAnswer": [
            "To repair physical damage to film stock",
            "To enhance film resolution",
            "To add special effects to films"
          ],
          "Explanation": "Film scanning is used to create digital copies of films, allowing for easier storage, distribution, and restoration."
        },
        {
          "Question": "Which film preservation technique involves repairing broken film reels?",
          "TrueAnswer": "Film splicing",
          "FalseAnswer": [
            "Film cutting",
            "Film duplication",
            "Film projection"
          ],
          "Explanation": "Film splicing is a preservation technique that involves repairing broken film reels to ensure the film can be viewed without interruption."
        },
        {
          "Question": "What is the purpose of film reformatting in film restoration?",
          "TrueAnswer": "To convert film to a different aspect ratio",
          "FalseAnswer": [
            "To enhance film resolution",
            "To add special effects to films",
            "To remove film imperfections"
          ],
          "Explanation": "Film reformatting is used to convert film to a different aspect ratio, allowing it to be viewed on different screens or platforms."
        },
        {
          "Question": "Which film preservation technique involves removing scratches and blemishes from film stock?",
          "TrueAnswer": "Film restoration",
          "FalseAnswer": [
            "Film duplication",
            "Film colorization",
            "Film stabilization"
          ],
          "Explanation": "Film restoration is a preservation technique that involves removing scratches and blemishes from film stock to improve its visual quality."
        },
        {
          "Question": "What is the purpose of film editing in film restoration?",
          "TrueAnswer": "To remove unwanted footage and create a cohesive narrative",
          "FalseAnswer": [
            "To repair physical damage to film stock",
            "To enhance film resolution",
            "To add special effects to films"
          ],
          "Explanation": "Film editing is used in film restoration to remove unwanted footage and create a cohesive narrative for the restored film."
        },
        {
          "Question": "Which film preservation technique involves adding special effects to films?",
          "TrueAnswer": "Film special effects",
          "FalseAnswer": [
            "Film cleaning",
            "Film scanning",
            "Film repair"
          ],
          "Explanation": "Film special effects is a preservation technique that involves adding special effects to films during the restoration process."
        },
        {
          "Question": "What is the purpose of film resolution enhancement in film restoration?",
          "TrueAnswer": "To improve the clarity and detail of the film image",
          "FalseAnswer": [
            "To convert film to a digital format",
            "To add color to black and white films",
            "To stabilize shaky footage"
          ],
          "Explanation": "Film resolution enhancement is used to improve the clarity and detail of the film image during the restoration process."
        },
        {
          "Question": "Which film preservation technique involves preserving film reels in climate-controlled environments?",
          "TrueAnswer": "Film storage",
          "FalseAnswer": [
            "Film projection",
            "Film duplication",
            "Film repair"
          ],
          "Explanation": "Film storage is a preservation technique that involves preserving film reels in climate-controlled environments to prevent deterioration."
        },
        {
          "Question": "What is the purpose of film distribution in film restoration?",
          "TrueAnswer": "To make restored films available to audiences",
          "FalseAnswer": [
            "To repair physical damage to film stock",
            "To preserve film history",
            "To convert film to a digital format"
          ],
          "Explanation": "Film distribution is used to make restored films available to audiences through various platforms, such as theaters or streaming services."
        }
      ]
    }
  ]
}