{
  "theme": [
    {
      "Questions": {
        "theme": [
          {
            "Question": "What is the largest planet in our solar system?",
            "TrueAnswer": "Jupiter",
            "FalseAnswer": [
              "Neptune",
              "Saturn",
              "Mars"
            ],
            "Explanation": "Jupiter is the largest planet in our solar system, with a diameter of about 86,881 miles (139,822 kilometers). It is known for its giant storm, the Great Red Spot."
          },
          {
            "Question": "Which celestial body is known as Earth's sister planet?",
            "TrueAnswer": "Venus",
            "FalseAnswer": [
              "Mars",
              "Jupiter",
              "Saturn"
            ],
            "Explanation": "Venus is often called Earth's sister planet due to its similar size and mass. However, its harsh atmosphere makes it very different from Earth."
          },
          {
            "Question": "What is the name of the first space station launched by the Soviet Union in 1971?",
            "TrueAnswer": "Salyut 1",
            "FalseAnswer": [
              "Mir",
              "Skylab",
              "ISS"
            ],
            "Explanation": "Salyut 1 was the first space station in human history, launched by the Soviet Union. It paved the way for future space stations and orbital outposts."
          },
          {
            "Question": "Which moon of Jupiter is known for its potential to support life?",
            "TrueAnswer": "Europa",
            "FalseAnswer": [
              "Io",
              "Ganymede",
              "Callisto"
            ],
            "Explanation": "Europa is considered one of the best candidates for finding extraterrestrial life due to its subsurface ocean and potential for habitable conditions."
          },
          {
            "Question": "What is the estimated travel time to Mars with current space propulsion technology?",
            "TrueAnswer": "6-8 months",
            "FalseAnswer": [
              "1 month",
              "3-5 years",
              "10-12 months"
            ],
            "Explanation": "Current space propulsion technology would take approximately 6-8 months to travel from Earth to Mars, depending on the position of both planets in their orbits."
          },
          {
            "Question": "What is the term commonly used for the hypothetical proposal to build a large space habitat?",
            "TrueAnswer": "O'Neill cylinder",
            "FalseAnswer": [
              "Dyson sphere",
              "Von Neumann probe",
              "Terraforming"
            ],
            "Explanation": "An O'Neill cylinder is a proposed concept for a space settlement design. It involves a rotating cylinder to simulate gravity and harness solar energy for human habitation."
          },
          {
            "Question": "Which NASA mission aims to land the first woman and the next man on the Moon by 2024?",
            "TrueAnswer": "Artemis",
            "FalseAnswer": [
              "Apollo",
              "Cassini",
              "Juno"
            ],
            "Explanation": "The Artemis program seeks to return humans to the Moon, with a focus on sustainability for future exploration and the potential for Mars missions."
          },
          {
            "Question": "Which planet could potentially support human colonization due to its similar characteristics to Earth?",
            "TrueAnswer": "Mars",
            "FalseAnswer": [
              "Jupiter",
              "Saturn",
              "Neptune"
            ],
            "Explanation": "Mars is a prime candidate for human colonization due to its relatively similar day length, surface gravity, and potential for sustainable resource extraction."
          },
          {
            "Question": "What is the proposed concept of creating a human settlement on another celestial body or space object?",
            "TrueAnswer": "Space colonization",
            "FalseAnswer": [
              "Orbital station",
              "Space tourism",
              "Astrobiology"
            ],
            "Explanation": "Space colonization involves establishing a long-term human presence on another world, such as a planet, moon, or asteroid, with the aim of sustainable habitation and resource utilization."
          },
          {
            "Question": "Which space agency is known for its Artemis Accords, aiming to create a peaceful and transparent framework for lunar exploration?",
            "TrueAnswer": "NASA",
            "FalseAnswer": [
              "ESA",
              "Roscosmos",
              "CNSA"
            ],
            "Explanation": "NASA's Artemis Accords provide a set of principles and guidelines for lunar exploration and utilization, promoting cooperation and transparency among international partners."
          },
          {
            "Question": "What is the term for when a spacecraft changes its trajectory using a planet's gravity without using propulsion?",
            "TrueAnswer": "Gravity assist",
            "FalseAnswer": [
              "Orbital insertion",
              "Space docking",
              "Lunar landing"
            ],
            "Explanation": "Gravity assist is a technique used in space exploration to accelerate or redirect a spacecraft's trajectory by using the gravitational pull of a planet or other celestial body."
          },
          {
            "Question": "Which private space company has proposed ambitious plans for colonizing Mars under the project 'Starship'?",
            "TrueAnswer": "SpaceX",
            "FalseAnswer": [
              "Blue Origin",
              "Virgin Galactic",
              "Boeing"
            ],
            "Explanation": "SpaceX, led by Elon Musk, aims to establish a self-sustaining human settlement on Mars using their Starship spacecraft and leveraging reusable rocket technology."
          },
          {
            "Question": "What is the term for converting a celestial body to have Earth-like conditions for human habitation?",
            "TrueAnswer": "Terraforming",
            "FalseAnswer": [
              "Atmospheric escape",
              "Space mining",
              "Asteroid redirection"
            ],
            "Explanation": "Terraforming involves transforming the environment of a planet, moon, or other celestial body to make it habitable for Earth-based life, potentially through atmospheric and temperature modification."
          },
          {
            "Question": "Which concept involves the establishment of self-sustainable human habitats in outer space or on other celestial bodies?",
            "TrueAnswer": "Space settlement",
            "FalseAnswer": [
              "Deep space exploration",
              "Interstellar travel",
              "Galactic colonization"
            ],
            "Explanation": "Space settlement refers to creating permanent, self-sustaining communities in space, such as on the Moon, Mars, or artificial space habitats, with the goal of long-term human presence and resource utilization."
          },
          {
            "Question": "Which space mission successfully landed the first human on the Moon in 1969?",
            "TrueAnswer": "Apollo 11",
            "FalseAnswer": [
              "Voyager 1",
              "Hubble Space Telescope",
              "Curiosity rover"
            ],
            "Explanation": "Apollo 11, led by astronauts Neil Armstrong, Buzz Aldrin, and Michael Collins, achieved the first human landing on the Moon on July 20, 1969, during the historic space race."
          },
          {
            "Question": "What is the term for the depletion of a planet's or moon's natural resources due to human activities?",
            "TrueAnswer": "Planetary exhaustion",
            "FalseAnswer": [
              "Exoplanet discovery",
              "Astrophysical depletion",
              "Space erosion"
            ],
            "Explanation": "Planetary exhaustion refers to the potential depletion of vital resources on a planetary body, impacting its sustainability and habitability for human settlement and long-term exploration."
          },
          {
            "Question": "Which planet in our solar system has the largest volcano and canyon, making it a potential site for human settlement?",
            "TrueAnswer": "Mars",
            "FalseAnswer": [
              "Earth",
              "Venus",
              "Mercury"
            ],
            "Explanation": "Mars is home to Olympus Mons, the largest volcano, and Valles Marineris, the longest canyon in the solar system, offering potential geologic resources for future human colonization."
          },
          {
            "Question": "What is the term for a self-sustaining space habitat that simulates Earth's gravity through rotation?",
            "TrueAnswer": "Space colony",
            "FalseAnswer": [
              "Asteroid outpost",
              "Deep-space lab",
              "Interstellar hotel"
            ],
            "Explanation": "A space colony is a proposed habitat where humans can live and work in space, potentially on a planet, moon, asteroid, or artificial construct, ensuring long-term sustainability and habitation."
          },
          {
            "Question": "Which international initiative aims to establish a permanent human presence on Mars with a focus on cooperative, non-governmental collaboration?",
            "TrueAnswer": "Mars One",
            "FalseAnswer": [
              "ExoMars",
              "Mars Direct",
              "Mars Society"
            ],
            "Explanation": "Mars One, a private Dutch initiative, aimed to establish a permanent human settlement on Mars, emphasizing public participation and collaborative funding for the mission."
          },
          {
            "Question": "What is the term for using resources from space objects, such as asteroids or the Moon, to sustain human activities in space?",
            "TrueAnswer": "In-situ resource utilization (ISRU)",
            "FalseAnswer": [
              "Space debris reclamation",
              "Cosmic material recycling",
              "Celestial body mining"
            ],
            "Explanation": "ISRU involves extracting and using materials found in space for fuel, water, oxygen, and other resources, reducing the need to transport supplies from Earth and enabling sustainable space settlement."
          }
        ]
      }
    }
  ]
}